NibbleMayor/bit_mayor.v
module bit_mayor (
                  input      clk,
                  input      reset,
                  input      bm_a,
                  input      bm_b,
                  output reg bm_selector,
                  output reg bm_distintos
                  );

   always @ (posedge clk) begin
      if (reset) begin
         bm_selector <= 0;
         bm_distintos <= 0;
      end else begin
         case ({bm_a, bm_b})
           2'b00 : begin
              bm_selector <= bm_selector;
              bm_distintos <= 0;
           end
           2'b01 : begin
              bm_selector <= 1;
              bm_distintos <= 1;
           end
           2'b10 : begin
              bm_selector <= 0;
              bm_distintos <= 1;
           end
           2'b11 : begin
              bm_selector <= bm_selector;
              bm_distintos <= 0;
           end
         endcase // case ({bm_a, bm_b})
      end // end else if reset
   end // end always posedge clk

endmodule

NibbleMayor/bit_mayor_tb.v
`timescale 1ns/100ps
`include "bit_mayor.v"

module bit_mayor_tb ();
   initial begin
      $dumpfile("contador.vcd");
      $dumpvars();
   end

   reg clk;
   reg reset;
   wire bm_selector;
   wire bm_distintos;
   reg  a;
   reg  b;

   initial begin
      clk = 1;
      reset = 1;
      a = 0;
      b = 0;

      @(posedge clk);
      reset <= 0;

      // start test
      repeat (2) begin
         a <= ~a;
         repeat(4) begin
            b <= ~b;
            @ (posedge clk);
         end
         @ (posedge clk);
      end

      $finish();
   end // initial begin

   always
     begin
        #15 clk = ~clk;
     end

   bit_mayor bm_ (
                  .clk (clk),
                  .reset (reset),
                  .bm_a (a),
                  .bm_b (b),
                  .bm_selector (bm_selector),
                  .bm_distintos (bm_distintos)
                  );

endmodule // bit_mayor_tb

NibbleMayor/contador.vcd
$date
	Sat Jun  8 17:36:05 2019
$end
$version
	Icarus Verilog
$end
$timescale
	100ps
$end
$scope module bit_mayor_tb $end
$var wire 1 ! bm_selector $end
$var wire 1 " bm_distintos $end
$var reg 1 # a $end
$var reg 1 $ b $end
$var reg 1 % clk $end
$var reg 1 & reset $end
$scope module bm_ $end
$var wire 1 # bm_a $end
$var wire 1 $ bm_b $end
$var wire 1 % clk $end
$var wire 1 & reset $end
$var reg 1 " bm_distintos $end
$var reg 1 ! bm_selector $end
$upscope $end
$upscope $end
$enddefinitions $end
#0
$dumpvars
1&
1%
0$
0#
0"
0!
$end
#150
0%
#300
1$
1#
0&
1%
#450
0%
#600
0$
1%
#750
0%
#900
1$
1"
1%
#1050
0%
#1200
0"
0$
1%
#1350
0%
#1500
1"
1%
#1650
0%
#1800
1$
0#
1%
#1950
0%
#2100
0$
1!
1%
#2250
0%
#2400
0"
1$
1%
#2550
0%
#2700
0$
1"
1%
#2850
0%
#3000
0"
1%
