nm2/nm2.v
module nm2(
    input CLK,
    input RESET_L,
    input [15:0] NIBBLES,
    output reg [3:0] NIBBLE_MAYOR,
    output reg [1:0] ID_MAYOR
);
    reg [3:0] nib_l1, nib_l2, nibble_A, nibble_B, nibble_C, nibble_D;
    reg [1:0] id1, id2;

    always @(*) begin
        nib_l1 = 0;
        nib_l2 = 0;
        id1 = 0;
        id2 = 0;
        if (~RESET_L)begin
            nib_l1 = 0;
            nib_l2 = 0;
            id1 = 0;
            id2 = 0;
        end else begin
            if(nibble_A >= nibble_B) begin
                nib_l1 = nibble_A;
                id1 = 0;
            end else begin
                nib_l1 = nibble_B;
                id1 = 1;
            end
            if(nibble_C >= nibble_D) begin
                nib_l2 = nibble_C;
                id2 = 2;
            end else begin
                nib_l2 = nibble_D;
                id2 = 3;
            end
        end
    end

    always @(posedge CLK) begin
        if(~RESET_L) begin
            NIBBLE_MAYOR <= 0;
            ID_MAYOR <= 0;
            nibble_A <= 0;
            nibble_B <= 0;
            nibble_C <= 0;
            nibble_D <= 0;
        end else begin
            nibble_A<=NIBBLES[3:0];
            nibble_B<=NIBBLES[7:4];
            nibble_C<=NIBBLES[11:8];
            nibble_D<=NIBBLES[15:12];

            if(nib_l1 >= nib_l2) begin
                NIBBLE_MAYOR <= nib_l1;
                ID_MAYOR <= id1;
            end else begin
                NIBBLE_MAYOR <= nib_l2;
                ID_MAYOR <= id2;
            end
        end
    end
endmodule // nm2

nm2/nib_m_t.v
module nib_m_t(
    output reg CLK,
    output reg RESET_L,
    output reg [15:0] NIBBLES
);
    initial begin
        $dumpfile("result.vcd");
        $dumpvars;
        {RESET_L, NIBBLES} <= 0;
        @(posedge CLK); 
        RESET_L<=1;
        @(posedge CLK);
        @(posedge CLK);
        NIBBLES <= 'h1234;
        @(posedge CLK);
        @(posedge CLK);
        NIBBLES <= 'h1534;
        @(posedge CLK);
        @(posedge CLK);
        NIBBLES <= 'h1574;
        @(posedge CLK);
        @(posedge CLK);
        NIBBLES <= 'h8234;
        @(posedge CLK);
        @(posedge CLK);
        @(posedge CLK);
        @(posedge CLK);
        $finish;
    end
    initial	CLK <= 0;
    always	#2 CLK <= ~CLK;
    

endmodule // nib_m_t

nm2/nib_m_tb.v
`include "nm2.v"
`include "nib_m_t.v"

module nib_m_tb;

    /*AUTOWIRE*/
    // Beginning of automatic wires (for undeclared instantiated-module outputs)
    wire		CLK;			// From test of nib_m_t.v
    wire [1:0]		ID_MAYOR;		// From sel of nm2.v
    wire [15:0]		NIBBLES;		// From test of nib_m_t.v
    wire [3:0]		NIBBLE_MAYOR;		// From sel of nm2.v
    wire		RESET_L;		// From test of nib_m_t.v
    // End of automatics

    nib_m_t test(/*AUTOINST*/
		 // Outputs
		 .CLK			(CLK),
		 .RESET_L		(RESET_L),
		 .NIBBLES		(NIBBLES[15:0]));


    nm2 sel(/*AUTOINST*/
	    // Outputs
	    .NIBBLE_MAYOR		(NIBBLE_MAYOR[3:0]),
	    .ID_MAYOR			(ID_MAYOR[1:0]),
	    // Inputs
	    .CLK			(CLK),
	    .RESET_L			(RESET_L),
	    .NIBBLES			(NIBBLES[15:0]));




endmodule

nm2/result.vcd
$date
	Thu Jun 27 22:55:53 2019
$end
$version
	Icarus Verilog
$end
$timescale
	1s
$end
$scope module nib_m_tb $end
$var wire 1 ! RESET_L $end
$var wire 4 " NIBBLE_MAYOR [3:0] $end
$var wire 16 # NIBBLES [15:0] $end
$var wire 2 $ ID_MAYOR [1:0] $end
$var wire 1 % CLK $end
$scope module sel $end
$var wire 1 ! RESET_L $end
$var wire 16 & NIBBLES [15:0] $end
$var wire 1 % CLK $end
$var reg 2 ' ID_MAYOR [1:0] $end
$var reg 4 ( NIBBLE_MAYOR [3:0] $end
$var reg 2 ) id1 [1:0] $end
$var reg 2 * id2 [1:0] $end
$var reg 4 + nib_l1 [3:0] $end
$var reg 4 , nib_l2 [3:0] $end
$var reg 4 - nibble_A [3:0] $end
$var reg 4 . nibble_B [3:0] $end
$var reg 4 / nibble_C [3:0] $end
$var reg 4 0 nibble_D [3:0] $end
$upscope $end
$scope module test $end
$var reg 1 % CLK $end
$var reg 16 1 NIBBLES [15:0] $end
$var reg 1 ! RESET_L $end
$upscope $end
$upscope $end
$enddefinitions $end
#0
$dumpvars
b0 1
bx 0
bx /
bx .
bx -
b0 ,
b0 +
b0 *
b0 )
bx (
bx '
b0 &
0%
bx $
b0 #
bx "
0!
$end
#2
b10 *
1!
b0 0
b0 /
b0 .
b0 -
b0 $
b0 '
b0 "
b0 (
1%
#4
0%
#6
1%
#8
0%
#10
b1001000110100 #
b1001000110100 &
b1001000110100 1
1%
#12
0%
#14
b10 ,
b100 +
b10 *
b1 0
b10 /
b11 .
b100 -
1%
#16
0%
#18
b1010100110100 #
b1010100110100 &
b1010100110100 1
b100 "
b100 (
1%
#20
0%
#22
b10 *
b101 ,
b100 +
b101 /
1%
#24
0%
#26
b1010101110100 #
b1010101110100 &
b1010101110100 1
b10 $
b10 '
b101 "
b101 (
1%
#28
0%
#30
b1 )
b10 *
b101 ,
b111 +
b111 .
1%
#32
0%
#34
b1000001000110100 #
b1000001000110100 &
b1000001000110100 1
b1 $
b1 '
b111 "
b111 (
1%
#36
0%
#38
b11 *
b0 )
b1000 ,
b100 +
b1000 0
b10 /
b11 .
1%
#40
0%
#42
b11 $
b11 '
b1000 "
b1000 (
1%
